tablesleuth/__init__.py
tablesleuth/config.py
tablesleuth/exceptions.py
tablesleuth/cli/__init__.py
tablesleuth/cli/config_check.py
tablesleuth/cli/delta.py
tablesleuth/cli/helpers.py
tablesleuth/cli/iceberg.py
tablesleuth/cli/init.py
tablesleuth/cli/parquet.py
tablesleuth/models/__init__.py
tablesleuth/models/file_ref.py
tablesleuth/models/iceberg.py
tablesleuth/models/parquet.py
tablesleuth/models/performance.py
tablesleuth/models/profiling.py
tablesleuth/models/snapshot.py
tablesleuth/models/table.py
tablesleuth/services/__init__.py
tablesleuth/services/delta_forensics.py
tablesleuth/services/file_discovery.py
tablesleuth/services/filesystem.py
tablesleuth/services/iceberg_metadata_service.py
tablesleuth/services/mor_service.py
tablesleuth/services/parquet_service.py
tablesleuth/services/snapshot_performance_analyzer.py
tablesleuth/services/snapshot_test_manager.py
tablesleuth/services/formats/__init__.py
tablesleuth/services/formats/base.py
tablesleuth/services/formats/delta.py
tablesleuth/services/formats/delta_filesystem.py
tablesleuth/services/formats/delta_log_parser.py
tablesleuth/services/formats/delta_utils.py
tablesleuth/services/formats/iceberg.py
tablesleuth/services/profiling/__init__.py
tablesleuth/services/profiling/backend_base.py
tablesleuth/services/profiling/fake_backend.py
tablesleuth/services/profiling/gizmo_duckdb.py
tablesleuth/tui/__init__.py
tablesleuth/tui/app.py
tablesleuth/tui/views/__init__.py
tablesleuth/tui/views/data_sample_view.py
tablesleuth/tui/views/delta_view.py
tablesleuth/tui/views/file_detail_view.py
tablesleuth/tui/views/file_list_view.py
tablesleuth/tui/views/iceberg_view.py
tablesleuth/tui/views/profile_view.py
tablesleuth/tui/views/row_groups_view.py
tablesleuth/tui/views/schema_view.py
tablesleuth/tui/views/snapshot_comparison_view.py
tablesleuth/tui/views/snapshot_detail_view.py
tablesleuth/tui/views/structure_view.py
tablesleuth/tui/widgets/__init__.py
tablesleuth/tui/widgets/loading.py
tablesleuth-0.5.3.dist-info/METADATA
tablesleuth-0.5.3.dist-info/WHEEL
tablesleuth-0.5.3.dist-info/entry_points.txt
tablesleuth-0.5.3.dist-info/licenses/LICENSE
tablesleuth-0.5.3.dist-info/RECORD
