Metadata-Version: 2.4
Name: tablesleuth
Version: 0.5.3
Summary: TableSleuth - a Textual TUI for Open Table Format forensics (Iceberg, Delta Lake) with data profiling.
Project-URL: Homepage, https://tablesleuth.com
Project-URL: Repository, https://github.com/jamesbconner/TableSleuth
Project-URL: Documentation, https://github.com/jamesbconner/TableSleuth/tree/main/docs
Project-URL: Bug Reports, https://github.com/jamesbconner/TableSleuth/issues
Project-URL: Changelog, https://github.com/jamesbconner/TableSleuth/blob/main/CHANGELOG.md
Author-email: James Conner <jamesbconner@gmail.com>
License: Apache-2.0
License-File: LICENSE
Keywords: analytics,aws,cli,data-engineering,data-lake,data-profiling,data-quality,delta-lake,duckdb,iceberg,lakehouse,metadata,parquet,pyarrow,s3,s3tables,schema,terminal,textual,tui
Classifier: Development Status :: 4 - Beta
Classifier: Environment :: Console
Classifier: Intended Audience :: Developers
Classifier: Intended Audience :: System Administrators
Classifier: License :: OSI Approved :: Apache Software License
Classifier: Operating System :: OS Independent
Classifier: Programming Language :: Python :: 3
Classifier: Programming Language :: Python :: 3 :: Only
Classifier: Programming Language :: Python :: 3.13
Classifier: Programming Language :: Python :: 3.14
Classifier: Topic :: Database
Classifier: Topic :: File Formats
Classifier: Topic :: Scientific/Engineering
Classifier: Topic :: Scientific/Engineering :: Information Analysis
Classifier: Topic :: Software Development :: Libraries :: Python Modules
Classifier: Topic :: System :: Benchmark
Classifier: Topic :: System :: Distributed Computing
Classifier: Topic :: System :: Monitoring
Classifier: Topic :: Utilities
Classifier: Typing :: Typed
Requires-Python: <3.15,>=3.13
Requires-Dist: adbc-driver-flightsql>=1.7.0
Requires-Dist: boto3>=1.35.0
Requires-Dist: click>=8.1.0
Requires-Dist: deltalake>=0.22.0
Requires-Dist: duckdb>=1.1.0
Requires-Dist: pandas>=2.3.0
Requires-Dist: pip>=24.0
Requires-Dist: pyarrow>=22.0.0
Requires-Dist: pydantic>=2.11.0
Requires-Dist: pyiceberg[glue,s3fs,sql-sqlite]>=0.9.1
Requires-Dist: pyyaml>=6.0.0
Requires-Dist: rich>=13.0.0
Requires-Dist: sqlalchemy>=2.0.0
Requires-Dist: textual>=0.86.2
Requires-Dist: uv>=0.5.0
Provides-Extra: dev
Requires-Dist: bandit[toml]<2.0.0,>=1.8.6; extra == 'dev'
Requires-Dist: build<2.0.0,>=1.0.0; extra == 'dev'
Requires-Dist: hypothesis<7.0.0,>=6.100.0; extra == 'dev'
Requires-Dist: mypy<2.0.0,>=1.18.2; extra == 'dev'
Requires-Dist: pre-commit<5.0.0,>=4.4.0; extra == 'dev'
Requires-Dist: pytest-asyncio<1.0.0,>=0.26.0; extra == 'dev'
Requires-Dist: pytest-cov<7.0.0,>=6.0.0; extra == 'dev'
Requires-Dist: pytest<9.0.0,>=8.4.2; extra == 'dev'
Requires-Dist: ruff<0.15.0,>=0.14.4; extra == 'dev'
Requires-Dist: textual-dev<2.0.0,>=1.7.0; extra == 'dev'
Requires-Dist: twine<6.0.0,>=5.0.0; extra == 'dev'
Requires-Dist: types-pyyaml; extra == 'dev'
Requires-Dist: types-toml; extra == 'dev'
